<?xml version="1.0" encoding="utf-8"?>
<Document>
  <Engineering version="V17" />
  <DocumentInfo>
    <Created>2024-10-17T14:16:18.3999577Z</Created>
    <ExportSetting>WithDefaults</ExportSetting>
    <InstalledProducts>
      <Product>
        <DisplayName>Totally Integrated Automation Portal</DisplayName>
        <DisplayVersion>V17 Update 4</DisplayVersion>
      </Product>
      <OptionPackage>
        <DisplayName>TIA Portal Openness</DisplayName>
        <DisplayVersion>V17 Update 4</DisplayVersion>
      </OptionPackage>
      <OptionPackage>
        <DisplayName>TIA Portal Version Control Interface</DisplayName>
        <DisplayVersion>V17</DisplayVersion>
      </OptionPackage>
      <Product>
        <DisplayName>SINAMICS Startdrive Advanced</DisplayName>
        <DisplayVersion>V17 Update2</DisplayVersion>
      </Product>
      <OptionPackage>
        <DisplayName>SINAMICS Startdrive G130, G150, S120, S150, SINAMICS MV, S210</DisplayName>
        <DisplayVersion>V17 Update2</DisplayVersion>
      </OptionPackage>
      <OptionPackage>
        <DisplayName>SINAMICS Startdrive G110M, G120, G120C, G120D, G120P, G115D</DisplayName>
        <DisplayVersion>V17 Update2</DisplayVersion>
      </OptionPackage>
      <Product>
        <DisplayName>STEP 7 Professional</DisplayName>
        <DisplayVersion>V17 Update 4</DisplayVersion>
      </Product>
      <OptionPackage>
        <DisplayName>STEP 7 Safety</DisplayName>
        <DisplayVersion>V17</DisplayVersion>
      </OptionPackage>
      <Product>
        <DisplayName>WinCC Advanced / Unified PC</DisplayName>
        <DisplayVersion>V17 Update 4</DisplayVersion>
      </Product>
    </InstalledProducts>
  </DocumentInfo>
  <SW.Types.PlcStruct ID="0">
    <AttributeList>
      <Interface><Sections xmlns="http://www.siemens.com/automation/Openness/SW/Interface/v5">
  <Section Name="None">
    <Member Name="ID" Datatype="DInt"><AttributeList><BooleanAttribute Name="ExternalAccessible" SystemDefined="true">true</BooleanAttribute><BooleanAttribute Name="ExternalVisible" SystemDefined="true">true</BooleanAttribute><BooleanAttribute Name="ExternalWritable" SystemDefined="true">false</BooleanAttribute><BooleanAttribute Name="SetPoint" SystemDefined="true">false</BooleanAttribute></AttributeList><Comment><MultiLanguageText Lang="en-US">ID Number for each Product Stream. The product IDs are used to report product identity for each product stream</MultiLanguageText></Comment></Member>
    <Member Name="Name" Datatype="String[80]"><AttributeList><BooleanAttribute Name="ExternalAccessible" SystemDefined="true">true</BooleanAttribute><BooleanAttribute Name="ExternalVisible" SystemDefined="true">true</BooleanAttribute><BooleanAttribute Name="ExternalWritable" SystemDefined="true">false</BooleanAttribute><BooleanAttribute Name="SetPoint" SystemDefined="true">false</BooleanAttribute></AttributeList><Comment><MultiLanguageText Lang="en-US">Name of Product Stream. The Name element is used to further report the identity of the product within the product stream, especially when alphanumeric characters are used (i.e. SKU or UPC)</MultiLanguageText></Comment></Member>
    <Member Name="Unit" Datatype="String[6]"><AttributeList><BooleanAttribute Name="ExternalAccessible" SystemDefined="true">true</BooleanAttribute><BooleanAttribute Name="ExternalVisible" SystemDefined="true">true</BooleanAttribute><BooleanAttribute Name="ExternalWritable" SystemDefined="true">false</BooleanAttribute><BooleanAttribute Name="SetPoint" SystemDefined="true">false</BooleanAttribute></AttributeList><Comment><MultiLanguageText Lang="en-US">Unit of Measure of each Product Stream. The Unit element is used to report the unit of production for the product within the product stream. An example product unit of measure may be Pc, Crtn, Case, etc</MultiLanguageText></Comment></Member>
    <Member Name="PrimaryQty" Datatype="Real"><AttributeList><BooleanAttribute Name="ExternalAccessible" SystemDefined="true">true</BooleanAttribute><BooleanAttribute Name="ExternalVisible" SystemDefined="true">true</BooleanAttribute><BooleanAttribute Name="ExternalWritable" SystemDefined="true">false</BooleanAttribute><BooleanAttribute Name="SetPoint" SystemDefined="true">false</BooleanAttribute></AttributeList><Comment><MultiLanguageText Lang="en-US">Product Primary Quantity Value of each Product Stream. The PrimaryQty element is used to provide a common reference for manufacturing throughput across all the machines on a production line. This element relates the number of Primary Products per Unit for a particular product stream. It can be used as a conversion factor for a local machine reference speed since Command.MachSpeed is given in units of PrimaryProducts/Min</MultiLanguageText></Comment></Member>
    <Member Name="ConsumedCount" Datatype="DInt"><AttributeList><BooleanAttribute Name="ExternalAccessible" SystemDefined="true">true</BooleanAttribute><BooleanAttribute Name="ExternalVisible" SystemDefined="true">true</BooleanAttribute><BooleanAttribute Name="ExternalWritable" SystemDefined="true">false</BooleanAttribute><BooleanAttribute Name="SetPoint" SystemDefined="true">false</BooleanAttribute></AttributeList><Comment><MultiLanguageText Lang="en-US">Consumed Count of each Product Stream. This tag represents the material used/consumed in the production machine for a particular input or output product stream. An example of tag usage would be the number of bags consumed in a filler, or bagger packaging machine, or the amount of linear length used, or the number caps used</MultiLanguageText></Comment></Member>
    <Member Name="ProcessedCount" Datatype="DInt"><AttributeList><BooleanAttribute Name="ExternalAccessible" SystemDefined="true">true</BooleanAttribute><BooleanAttribute Name="ExternalVisible" SystemDefined="true">true</BooleanAttribute><BooleanAttribute Name="ExternalWritable" SystemDefined="true">false</BooleanAttribute><BooleanAttribute Name="SetPoint" SystemDefined="true">false</BooleanAttribute></AttributeList><Comment><MultiLanguageText Lang="en-US">Processed Count of each Product Stream. This tag represents the number of products from a particular input or output product stream processed by the production machine. An example of tag usage would be the number of products that were made, including all good and defective products. The number of products processed minus the number of defective products is the number of products actually made by the machine. Minimum required for information/machine monitoring</MultiLanguageText></Comment></Member>
    <Member Name="DefectiveCount" Datatype="DInt"><AttributeList><BooleanAttribute Name="ExternalAccessible" SystemDefined="true">true</BooleanAttribute><BooleanAttribute Name="ExternalVisible" SystemDefined="true">true</BooleanAttribute><BooleanAttribute Name="ExternalWritable" SystemDefined="true">false</BooleanAttribute><BooleanAttribute Name="SetPoint" SystemDefined="true">false</BooleanAttribute></AttributeList><Comment><MultiLanguageText Lang="en-US">Defective Count of each Product Stream. This tag represents the number of products from a particular input or output product stream that is marked as defective in the production machine, to be used if applicable. An example of tag usage would be the number of products rejected or products that are termed defective. Minimum required for information/machine monitoring</MultiLanguageText></Comment></Member>
    <Member Name="AccConsumedCount" Datatype="DInt"><AttributeList><BooleanAttribute Name="ExternalAccessible" SystemDefined="true">true</BooleanAttribute><BooleanAttribute Name="ExternalVisible" SystemDefined="true">true</BooleanAttribute><BooleanAttribute Name="ExternalWritable" SystemDefined="true">false</BooleanAttribute><BooleanAttribute Name="SetPoint" SystemDefined="true">false</BooleanAttribute></AttributeList><Comment><MultiLanguageText Lang="en-US">Accumulated Consumption Count of each Product Stream Consumption Since Last Reset. This tag represents the total accumulated material used/consumed in the production machine for a particular input or output product stream</MultiLanguageText></Comment></Member>
    <Member Name="AccProcessedCount" Datatype="DInt"><AttributeList><BooleanAttribute Name="ExternalAccessible" SystemDefined="true">true</BooleanAttribute><BooleanAttribute Name="ExternalVisible" SystemDefined="true">true</BooleanAttribute><BooleanAttribute Name="ExternalWritable" SystemDefined="true">false</BooleanAttribute><BooleanAttribute Name="SetPoint" SystemDefined="true">false</BooleanAttribute></AttributeList><Comment><MultiLanguageText Lang="en-US">Accumulated Processed Count of each Product Stream Since Last Reset. This tag represents the total accumulated number of products from a particular input or output product stream processed by the production machine. An example of tag usage would be the number of products that were made, including all good and defective products. The number of products processed minus the number of defective products is the number of products actually made by the machine</MultiLanguageText></Comment></Member>
    <Member Name="AccDefectiveCount" Datatype="DInt"><AttributeList><BooleanAttribute Name="ExternalAccessible" SystemDefined="true">true</BooleanAttribute><BooleanAttribute Name="ExternalVisible" SystemDefined="true">true</BooleanAttribute><BooleanAttribute Name="ExternalWritable" SystemDefined="true">false</BooleanAttribute><BooleanAttribute Name="SetPoint" SystemDefined="true">false</BooleanAttribute></AttributeList><Comment><MultiLanguageText Lang="en-US">Accumulated Defective Count of each Product Stream Since Last Reset. This tag represents the total accumulated number of products from a particular input or output product stream that is marked as defective in the production machine, to be used if applicable. An example of tag usage would be the number of products rejected or products that are termed defective</MultiLanguageText></Comment></Member>
  </Section>
</Sections></Interface>
      <IsFailsafeCompliant>false</IsFailsafeCompliant>
      <Name>LPMLV2022_typeProductData</Name>
    </AttributeList>
    <ObjectList>
      <MultilingualText ID="1" CompositionName="Comment">
        <ObjectList>
          <MultilingualTextItem ID="2" CompositionName="Items">
            <AttributeList>
              <Culture>en-US</Culture>
              <Text>Support: tech.team.motioncontrol@siemens.com</Text>
            </AttributeList>
          </MultilingualTextItem>
        </ObjectList>
      </MultilingualText>
      <MultilingualText ID="3" CompositionName="Title">
        <ObjectList>
          <MultilingualTextItem ID="4" CompositionName="Items">
            <AttributeList>
              <Culture>en-US</Culture>
              <Text>LPMLV2022_typeProductData</Text>
            </AttributeList>
          </MultilingualTextItem>
        </ObjectList>
      </MultilingualText>
    </ObjectList>
  </SW.Types.PlcStruct>
</Document>